__init__.py
bee_py/Exceptions.py
bee_py/__init__.py
bee_py/bee.py
bee_py/bee_debug.py
bee_py/py.typed
bee_py/chunk/__init__.py
bee_py/chunk/bmt.py
bee_py/chunk/cac.py
bee_py/chunk/serialize.py
bee_py/chunk/signer.py
bee_py/chunk/soc.py
bee_py/chunk/span.py
bee_py/feed/__init__.py
bee_py/feed/feed.py
bee_py/feed/identifiers.py
bee_py/feed/json.py
bee_py/feed/retrievable.py
bee_py/feed/topic.py
bee_py/feed/type.py
bee_py/modules/__init__.py
bee_py/modules/bytes.py
bee_py/modules/bzz.py
bee_py/modules/chunk.py
bee_py/modules/feed.py
bee_py/modules/pinning.py
bee_py/modules/pss.py
bee_py/modules/soc.py
bee_py/modules/status.py
bee_py/modules/stewardship.py
bee_py/modules/tag.py
bee_py/modules/debug/__init__.py
bee_py/modules/debug/balance.py
bee_py/modules/debug/chequebook.py
bee_py/modules/debug/chunk.py
bee_py/modules/debug/connectivity.py
bee_py/modules/debug/settlements.py
bee_py/modules/debug/stake.py
bee_py/modules/debug/stamps.py
bee_py/modules/debug/states.py
bee_py/modules/debug/status.py
bee_py/modules/debug/tag.py
bee_py/modules/debug/transactions.py
bee_py/types/__init__.py
bee_py/types/debug.py
bee_py/types/type.py
bee_py/utils/__init__.py
bee_py/utils/bytes.py
bee_py/utils/collection.py
bee_py/utils/collection_node.py
bee_py/utils/data.py
bee_py/utils/error.py
bee_py/utils/eth.py
bee_py/utils/hash.py
bee_py/utils/headers.py
bee_py/utils/hex.py
bee_py/utils/http.py
bee_py/utils/logging.py
bee_py/utils/pss.py
bee_py/utils/reference.py
bee_py/utils/stamps.py
bee_py/utils/tar.py
bee_py/utils/type.py
bee_py/utils/urls.py
swarm_bee_py-0.1.1.dist-info/LICENSE
swarm_bee_py-0.1.1.dist-info/METADATA
swarm_bee_py-0.1.1.dist-info/WHEEL
swarm_bee_py-0.1.1.dist-info/top_level.txt
swarm_bee_py-0.1.1.dist-info/RECORD
