Metadata-Version: 2.1
Name: swarm-bee-py
Version: 0.1.1
Summary: Python client library for connecting to Bee decentralised storage
Author-email: SAIKAT KARMAKAR <saikickkarma@protonmail.com>
License: LGPL-3.0, GPL-3.0
Project-URL: homepage, https://github.com/alienrobotninja/bee-py
Project-URL: repository, https://github.com/alienrobotninja/bee-py
Project-URL: Issues, https://github.com/alienrobotninja/bee-py/issues
Project-URL: Changelog, https://github.com/alienrobotninja/bee-py/releases
Classifier: Development Status :: 2 - Pre-Alpha
Classifier: Programming Language :: Python
Classifier: Programming Language :: Python :: 3.9
Classifier: Programming Language :: Python :: 3.10
Classifier: Programming Language :: Python :: 3.11
Classifier: Programming Language :: Python :: Implementation :: CPython
Classifier: Programming Language :: Python :: Implementation :: PyPy
Requires-Python: >=3.9
License-File: LICENSE
Requires-Dist: structlog >=23.2.0
Requires-Dist: semver >=3.0.2
Requires-Dist: websocket-client >=1.6.4
Requires-Dist: eth-pydantic-types >=0.1.0a3
Requires-Dist: web3 >=6.12.0
Requires-Dist: deepmerge >=1.1.1
Requires-Dist: eth-ape >=0.7.0
Requires-Dist: swarm-cid-py >=0.1.3
Requires-Dist: ecdsa >=0.18.0
